glue_jupyter/__init__.py
glue_jupyter/app.py
glue_jupyter/conftest.py
glue_jupyter/data.py
glue_jupyter/ipywidgets_layout.py
glue_jupyter/layout_widget.vue
glue_jupyter/link.py
glue_jupyter/registries.py
glue_jupyter/state_traitlets_helpers.py
glue_jupyter/utils.py
glue_jupyter/view.py
glue_jupyter/vuetify_helpers.py
glue_jupyter/vuetify_layout.py
glue_jupyter/bqplot/__init__.py
glue_jupyter/bqplot/compatibility.py
glue_jupyter/bqplot/common/__init__.py
glue_jupyter/bqplot/common/tools.py
glue_jupyter/bqplot/common/viewer.py
glue_jupyter/bqplot/histogram/__init__.py
glue_jupyter/bqplot/histogram/layer_artist.py
glue_jupyter/bqplot/histogram/viewer.py
glue_jupyter/bqplot/histogram/tests/__init__.py
glue_jupyter/bqplot/histogram/tests/test_viewer.py
glue_jupyter/bqplot/image/__init__.py
glue_jupyter/bqplot/image/frb_mark.py
glue_jupyter/bqplot/image/layer_artist.py
glue_jupyter/bqplot/image/state.py
glue_jupyter/bqplot/image/viewer.py
glue_jupyter/bqplot/image/tests/__init__.py
glue_jupyter/bqplot/image/tests/test_viewer.py
glue_jupyter/bqplot/image/tests/test_visual.py
glue_jupyter/bqplot/profile/__init__.py
glue_jupyter/bqplot/profile/layer_artist.py
glue_jupyter/bqplot/profile/viewer.py
glue_jupyter/bqplot/profile/tests/__init__.py
glue_jupyter/bqplot/profile/tests/test_viewer.py
glue_jupyter/bqplot/scatter/__init__.py
glue_jupyter/bqplot/scatter/layer_artist.py
glue_jupyter/bqplot/scatter/scatter_density_mark.py
glue_jupyter/bqplot/scatter/viewer.py
glue_jupyter/bqplot/scatter/tests/__init__.py
glue_jupyter/bqplot/scatter/tests/test_viewer.py
glue_jupyter/bqplot/scatter/tests/test_visual.py
glue_jupyter/bqplot/tests/__init__.py
glue_jupyter/bqplot/tests/test_bqplot.py
glue_jupyter/bqplot/tests/data/bqplot.ipynb
glue_jupyter/common/__init__.py
glue_jupyter/common/basic_jupyter_toolbar.vue
glue_jupyter/common/slice_helpers.py
glue_jupyter/common/state3d.py
glue_jupyter/common/toolbar_vuetify.py
glue_jupyter/common/state_widgets/__init__.py
glue_jupyter-0.24.0.dist-info/licenses/LICENSE
glue_jupyter-0.24.0.dist-info/METADATA
glue_jupyter-0.24.0.dist-info/WHEEL
glue_jupyter-0.24.0.dist-info/top_level.txt
glue_jupyter-0.24.0.dist-info/RECORD
