Metadata-Version: 2.4
Name: glue-jupyter
Version: 0.24.0
Summary: Jupyter notebook/lab viewers for glue
Home-page: https://glueviz.org
Author: Maarten A. Breddels and Thomas Robitaille
Author-email: maartenbreddels@gmail.com
License: BSD License
Requires-Python: >=3.8
License-File: LICENSE
Requires-Dist: glue-core>=1.20.0
Requires-Dist: glue-vispy-viewers[jupyter]>=1.2.1
Requires-Dist: notebook>=4.0
Requires-Dist: ipython_genutils>=0.2
Requires-Dist: ipympl>=0.3.0
Requires-Dist: ipyvolume>=0.5.0
Requires-Dist: ipyvolume>=0.6.0a10; python_version >= "3.8"
Requires-Dist: ipython_genutils>=0.2
Requires-Dist: ipywidgets>=7.4.0
Requires-Dist: ipyvue<2,>=1.2.0
Requires-Dist: ipyvuetify<2,>=1.2.0
Requires-Dist: bqplot-image-gl>=1.6.0
Requires-Dist: bqplot>=0.12.17
Requires-Dist: bqplot-gl
Requires-Dist: scikit-image
Provides-Extra: test
Requires-Dist: pytest; extra == "test"
Requires-Dist: pytest-cov; extra == "test"
Requires-Dist: nbconvert>=6.4.5; extra == "test"
Provides-Extra: visualtest
Requires-Dist: playwright==1.41.2; extra == "visualtest"
Requires-Dist: pytest-playwright==0.5.2; extra == "visualtest"
Requires-Dist: pytest-mpl; extra == "visualtest"
Requires-Dist: solara[pytest]>=1.44.1; extra == "visualtest"
Provides-Extra: docs
Requires-Dist: sphinx; extra == "docs"
Requires-Dist: sphinx-automodapi; extra == "docs"
Requires-Dist: numpydoc; extra == "docs"
Requires-Dist: nbconvert>=6.4.5; extra == "docs"
Requires-Dist: nbsphinx; extra == "docs"
Requires-Dist: sphinx-book-theme; extra == "docs"
Dynamic: license-file
